restfmclient/__init__.py
restfmclient/client.py
restfmclient/cursor.py
restfmclient/database.py
restfmclient/exceptions.py
restfmclient/layout.py
restfmclient/record.py
restfmclient/rest.py
restfmclient/script.py
restfmclient/types.py
restfmclient/util.py
restfmclient/version.py
restfmclient-1.2.1.dist-info/DESCRIPTION.rst
restfmclient-1.2.1.dist-info/METADATA
restfmclient-1.2.1.dist-info/RECORD
restfmclient-1.2.1.dist-info/WHEEL
restfmclient-1.2.1.dist-info/metadata.json
restfmclient-1.2.1.dist-info/top_level.txt
restfmclient-1.2.1.dist-info/zip-safe
