Metadata-Version: 2.0
Name: restfmclient
Version: 1.2.1
Summary: Python client library for RESTfm
Home-page: https://github.com/mariaebene/py-restfmclient
Author: René Jochum
Author-email: rene.jochum@mariaebene.at
License: MIT
Keywords: Python Filemaker RestFM
Platform: UNKNOWN
Classifier: Programming Language :: Python
Classifier: Programming Language :: Python :: 3.5
Requires-Dist: setuptools
Requires-Dist: aiohttp
Requires-Dist: simplejson
Requires-Dist: pytz
Requires-Dist: tzlocal
Provides-Extra: test
Requires-Dist: py-dateutil; extra == 'test'
